{
    "patches": [
        {
            "label": "2025-10-02_19-10-06",
            "content": "@@ -823,27 +823,15 @@\n == %22\n-init%22:%0A            \n+criar%22:\n %0A   \n",
            "lines": "46"
        },
        {
            "label": "2025-10-02_19-12-57",
            "content": "class Animal:\n    def __init__(self, species: str, sound: str):\n        self.species: str = species \n        self.sound: str = sound\n        self.age: int = 0\n\n    def ageBy(self, increment: int) -> None:\n        self.age += increment\n        if self.age >= 4:\n            self.age = 4\n            print (\"warning: {species} morreu\")\n\n    def makeSound(self) -> str:\n        if self.age == 0:\n            return \"---\"\n        if self.age >=4:\n            return \"RIP\"\n        else:\n            return self.sound\n        \n    def __str__(self) -> str:\n        return \"{species}:{age}:{sound}\" \n    \ndef main():\n    animal: Animal = Animal \n    while True:\n\n        line: str = input()\n        print(\"$\" + line)\n        args: list[str]  = line.split(\" \")\n\n        if args[0] == \"end\":\n            break\n        elif args[0] == \"init\":\n            \n            species: str = args[1]\n            sound: str = args[2]\n            animal = Animal(species,sound)\n        elif args[0] == \"grow\":\n            increment: int = int(args[1])\n            animal.ageBy(increment)\n        elif args[0] == \"show\":\n            print(animal)\n        elif args[0] == \"som\":\n            print(animal.makeSound())\n        else:\n            print (\"fail: comando n\u00e3o encontrado\") ",
            "lines": "47"
        }
    ]
}